kalbio/__init__.py
kalbio/_kaleidoscope_model.py
kalbio/activities.py
kalbio/client.py
kalbio/dashboards.py
kalbio/entity_fields.py
kalbio/entity_types.py
kalbio/exports.py
kalbio/helpers.py
kalbio/imports.py
kalbio/labels.py
kalbio/programs.py
kalbio/property_fields.py
kalbio/record_views.py
kalbio/records.py
kalbio/workspace.py
kalbio-0.2.1.dist-info/METADATA
kalbio-0.2.1.dist-info/WHEEL
kalbio-0.2.1.dist-info/RECORD
