Metadata-Version: 2.1
Name: kalbio
Version: 0.2.1
Summary: Python client for kaleidoscope.bio
License: MIT
Author: Ahmed Elnaiem
Author-email: ahmed@kaleidoscope.bio
Requires-Python: >=3.10,<4.0
Classifier: License :: OSI Approved :: MIT License
Classifier: Programming Language :: Python :: 3
Classifier: Programming Language :: Python :: 3.10
Classifier: Programming Language :: Python :: 3.11
Classifier: Programming Language :: Python :: 3.12
Requires-Dist: pydantic (>=2.9.2,<3.0.0)
Requires-Dist: requests (>=2.32.3,<3.0.0)
Project-URL: Documentation, https://api.docs.kaleidoscope.bio
Project-URL: Homepage, https://github.com/kaleidoscope-tech/kalbio
Project-URL: Repository, https://github.com/kaleidoscope-tech/kalbio
